README
setup.py
gcKISSmetrics.egg-info/PKG-INFO
gcKISSmetrics.egg-info/SOURCES.txt
gcKISSmetrics.egg-info/dependency_links.txt
gcKISSmetrics.egg-info/entry_points.txt
gcKISSmetrics.egg-info/top_level.txt
km/__init__.py
km/helpers/__init__.py
km/helpers/is_robot.py