Metadata-Version: 1.0
Name: gcKISSmetrics
Version: 1.0.3
Summary: Python API for KISSmetrics
Home-page: http://github.com/gamechanger/KISSmetrics-python
Author: KISSmetrics
Author-email: info@kissmetrics.com
License: Other/Proprietary License
Keywords: kissmetrics
Platform: UNKNOWN
